sphinxext/bsb/__init__.py
sphinxext/bsb/project.py
sphinxext_bsb-7.2.1.dist-info/licenses/LICENSE
sphinxext_bsb-7.2.1.dist-info/WHEEL
sphinxext_bsb-7.2.1.dist-info/METADATA
sphinxext_bsb-7.2.1.dist-info/RECORD
