Metadata-Version: 2.4
Name: sphinxext-bsb
Version: 7.2.1
Summary: BSB Sphinx documentation extension
Requires-Python: >=3.10,<4
Classifier: License :: OSI Approved :: GNU General Public License v3 or later (GPLv3+)
License-File: LICENSE
Requires-Dist: bsb-core~=7.0
Requires-Dist: sphinx>=8.1
Requires-Dist: sphinx-design~=0.6
